pysimple/exceptions.py
pysimple/account.py
pysimple/_metadata.py
pysimple/__init__.py
pysimple-0.1.9.dist-info/METADATA
pysimple-0.1.9.dist-info/pbr.json
pysimple-0.1.9.dist-info/WHEEL
pysimple-0.1.9.dist-info/DESCRIPTION.rst
pysimple-0.1.9.dist-info/top_level.txt
pysimple-0.1.9.dist-info/metadata.json
pysimple-0.1.9.dist-info/RECORD
