Metadata-Version: 1.1
Name: pysimple
Version: 0.1.9
Summary: Python library for Simple online bank
Home-page: https://github.com/TFenby/pysimple
Author: Tyler Fenby
Author-email: tylerfenby@gmail.com
License: GPLv3
Keywords: pysimple simple
Platform: UNKNOWN
Classifier: Development Status :: 4 - Beta
Classifier: Intended Audience :: Developers
Classifier: License :: OSI Approved :: GNU General Public License v3 (GPLv3)
Classifier: Natural Language :: English
Classifier: Programming Language :: Python :: 2
Classifier: Programming Language :: Python :: 2.6
Classifier: Programming Language :: Python :: 2.7
Classifier: Programming Language :: Python :: 3
Classifier: Programming Language :: Python :: 3.3
Classifier: Programming Language :: Python :: Implementation :: PyPy
